{
  "controllers": [
    {
      "params": {
        "thermal_process": "#room_004",
        "attribute": "on",
        "friendly_name": "thermostat_004",
        "hysteresis": "0.781892*delta_degC",
        "target_temperature": "293.247508*kelvin",
        "subject": "#heater_004"
      },
      "type": "Thermostat",
      "module": "devices"
    },
    {
      "params": {
        "thermal_process": "#boiler_004",
        "attribute": "on",
        "friendly_name": "thermostat_boiler_004",
        "hysteresis": "10*delta_degC",
        "target_temperature": "328.15*kelvin",
        "subject": "#boiler_004"
      },
      "type": "Thermostat",
      "module": "devices"
    }
  ],
  "thermal": [
    {
      "params": {
        "initial_temperature": "293.405767*kelvin",
        "thermal_capacity": "1003.859201*J/(kg*K)",
        "friendly_name": "room_004",
        "mass": "85.691320*metre*metre * 2.5*metre * 1.200*kg/(m**3)"
      },
      "type": "ThermalProcess",
      "module": "gridsim.thermal.core"
    },
    {
      "params": {
        "time_converter": "lambda t: t*units.hours",
        "time_series": "#default",
        "temperature_calculator": "lambda t: units.convert(units(t, units.degC), units.kelvin)",
        "friendly_name": "outside"
      },
      "type": "TimeSeriesThermalProcess",
      "module": "gridsim.thermal.element"
    },
    {
      "params": {
        "from_process": "#room_004",
        "to_process": "#outside",
        "friendly_name": "room_004 to outside",
        "thermal_conductivity": "8.015607*W/(K*m)"
      },
      "type": "ThermalCoupling",
      "module": "gridsim.thermal.core"
    }
  ],
  "electrical": {
    "attach": [
      {
        "device": "#heater_004",
        "bus": "Bus_004"
      },
      {
        "device": "#house_004",
        "bus": "Bus_004"
      },
      {
        "device": "#boiler_004",
        "bus": "Bus_004"
      }
    ],
    "branches": [
      {
        "two_port": "#Line_004",
        "bus_b": "Bus_004",
        "friendly_name": "Branch_004",
        "bus_a": "Slack Bus"
      }
    ],
    "devices": [
      {
        "params": {
          "X": "0.2*ohm",
          "length": "1*m",
          "friendly_name": "Line_004"
        },
        "type": "ElectricalTransmissionLine",
        "module": "gridsim.electrical.network"
      },
      {
        "params": {
          "thermal_process": "#room_004",
          "pwr": "1015.470785watt",
          "friendly_name": "heater_004",
          "efficiency_factor": "3.017716"
        },
        "type": "ElectroThermalHeaterCooler",
        "module": "devices"
      },
      {
        "params": {
          "time_converter": "lambda t: t*units.minute",
          "time_series": "#house_000004",
          "friendly_name": "house_004"
        },
        "type": "TimeSeriesElectricalCPSElement",
        "module": "gridsim.electrical.element"
      },
      {
        "params": {
          "temperature_in": "288.15*kelvin",
          "power": "2400*watt",
          "initial_temperature": "328.15*kelvin",
          "heat_transfer_coeff": "8*watt/(kelvin*(meter**2))",
          "friendly_name": "boiler_004",
          "time_series": "#boiler_000004",
          "thickness": "100mm",
          "time_converter": "lambda t: t*units.minute",
          "radius": "20cm",
          "height": "160cm"
        },
        "type": "Boiler",
        "module": "devices"
      }
    ],
    "buses": [
      {
        "params": {
          "friendly_name": "Bus_004"
        },
        "type": "ElectricalPQBus",
        "module": "gridsim.electrical.network"
      }
    ]
  },
  "time_series": [
    {
      "type": "SortedConstantStepTimeSeriesObject",
      "friendly_name": "default",
      "data": "../resources/demo/outside/default.csv",
      "module": "gridsim.timeseries",
      "reader": "CSVReader"
    },
    {
      "type": "SortedConstantStepTimeSeriesObject",
      "friendly_name": "house_000004",
      "data": "../resources/demo/houses/house_000004.csv",
      "module": "gridsim.timeseries",
      "reader": "CSVReader"
    },
    {
      "type": "SortedConstantStepTimeSeriesObject",
      "friendly_name": "boiler_000004",
      "data": "../resources/demo/boilers/house_000004.csv",
      "module": "gridsim.timeseries",
      "reader": "CSVReader"
    }
  ],
  "name": "Thermal demo"
}