{
  "controllers": [
    {
      "type": "Thermostat",
      "params": {
        "thermal_process": "#room_058",
        "attribute": "on",
        "friendly_name": "thermostat_058",
        "hysteresis": "2.635328*delta_degC",
        "target_temperature": "294.610965*kelvin",
        "subject": "#heater_058"
      },
      "module": "devices"
    },
    {
      "type": "Thermostat",
      "params": {
        "thermal_process": "#boiler_058",
        "attribute": "on",
        "friendly_name": "thermostat_boiler_058",
        "hysteresis": "10*delta_degC",
        "target_temperature": "328.15*kelvin",
        "subject": "#boiler_058"
      },
      "module": "devices"
    }
  ],
  "thermal": [
    {
      "type": "ThermalProcess",
      "params": {
        "initial_temperature": "295.358732*kelvin",
        "friendly_name": "room_058",
        "thermal_capacity": "2.969415*kWh/(kg*K)"
      },
      "module": "gridsim.thermal.core"
    },
    {
      "type": "TimeSeriesThermalProcess",
      "params": {
        "time_converter": "lambda t: t*units.hours",
        "time_series": "#example",
        "temperature_calculator": "lambda t: units.convert(units(t, units.degC), units.kelvin)",
        "friendly_name": "outside"
      },
      "module": "gridsim.thermal.element"
    },
    {
      "type": "ThermalCoupling",
      "params": {
        "from_process": "#room_058",
        "thermal_conductivity": "135.641062*W/(K*m)",
        "friendly_name": "room_058 to outside",
        "to_process": "#outside"
      },
      "module": "gridsim.thermal.core"
    }
  ],
  "electrical": {
    "attach": [
      {
        "device": "#heater_058",
        "bus": "Bus_058"
      },
      {
        "device": "#house_058",
        "bus": "Bus_058"
      },
      {
        "device": "#boiler_058",
        "bus": "Bus_058"
      }
    ],
    "branches": [
      {
        "two_port": "#Line_058",
        "friendly_name": "Branch_058",
        "bus_b": "Bus_058",
        "bus_a": "Slack Bus"
      }
    ],
    "devices": [
      {
        "type": "ElectricalTransmissionLine",
        "params": {
          "X": "0.2*ohm",
          "length": "1*m",
          "friendly_name": "Line_058"
        },
        "module": "gridsim.electrical.network"
      },
      {
        "type": "ElectroThermalHeaterCooler",
        "params": {
          "thermal_process": "#room_058",
          "friendly_name": "heater_058",
          "pwr": "1747.540214*watt",
          "efficiency_factor": "3.147281"
        },
        "module": "devices"
      },
      {
        "type": "TimeSeriesElectricalCPSElement",
        "params": {
          "time_converter": "lambda t: t*units.minute",
          "time_series": "#house_000058",
          "friendly_name": "house_058"
        },
        "module": "gridsim.electrical.element"
      },
      {
        "type": "Boiler",
        "params": {
          "temperature_in": "288.15*kelvin",
          "power": "2400*watt",
          "initial_temperature": "328.15*kelvin",
          "heat_transfer_coeff": "8*watt/(kelvin*(meter**2))",
          "friendly_name": "boiler_058",
          "time_series": "#boiler_000058",
          "thickness": "100mm",
          "time_converter": "lambda t: t*units.minute",
          "radius": "20cm",
          "height": "160cm"
        },
        "module": "devices"
      }
    ],
    "buses": [
      {
        "type": "ElectricalPQBus",
        "params": {
          "friendly_name": "Bus_058"
        },
        "module": "gridsim.electrical.network"
      }
    ]
  },
  "time_series": [
    {
      "friendly_name": "example",
      "reader": "CSVReader",
      "type": "SortedConstantStepTimeSeriesObject",
      "module": "gridsim.timeseries",
      "data": "../resources/demo/outside/default.csv"
    },
    {
      "friendly_name": "house_000058",
      "reader": "CSVReader",
      "type": "SortedConstantStepTimeSeriesObject",
      "module": "gridsim.timeseries",
      "data": "../resources/demo/houses/house_000058.csv"
    },
    {
      "friendly_name": "boiler_000058",
      "reader": "CSVReader",
      "type": "SortedConstantStepTimeSeriesObject",
      "module": "gridsim.timeseries",
      "data": "../resources/demo/boilers/house_000058.csv"
    }
  ],
  "name": "058"
}